odoo/addons/account_invoice_inter_company_queued/README.rst
odoo/addons/account_invoice_inter_company_queued/__init__.py
odoo/addons/account_invoice_inter_company_queued/__manifest__.py
odoo/addons/account_invoice_inter_company_queued/i18n/account_invoice_inter_company_queued.pot
odoo/addons/account_invoice_inter_company_queued/i18n/it.po
odoo/addons/account_invoice_inter_company_queued/models/__init__.py
odoo/addons/account_invoice_inter_company_queued/models/account_move.py
odoo/addons/account_invoice_inter_company_queued/models/res_config_settings.py
odoo/addons/account_invoice_inter_company_queued/readme/CONFIGURE.rst
odoo/addons/account_invoice_inter_company_queued/readme/CONTRIBUTORS.rst
odoo/addons/account_invoice_inter_company_queued/readme/DESCRIPTION.rst
odoo/addons/account_invoice_inter_company_queued/static/description/icon.png
odoo/addons/account_invoice_inter_company_queued/static/description/index.html
odoo/addons/account_invoice_inter_company_queued/views/res_config_settings_view.xml
odoo14_addon_account_invoice_inter_company_queued-14.0.1.0.1.dist-info/METADATA
odoo14_addon_account_invoice_inter_company_queued-14.0.1.0.1.dist-info/WHEEL
odoo14_addon_account_invoice_inter_company_queued-14.0.1.0.1.dist-info/top_level.txt
odoo14_addon_account_invoice_inter_company_queued-14.0.1.0.1.dist-info/RECORD
